{"is_source_file": true, "format": "TypeScript (React JSX)", "description": "This file defines a React functional component called Footer which renders a footer element with some styling and copyright information.", "external_files": [], "external_methods": [], "published": ["Footer"], "classes": [], "methods": [{"name": "Footer", "description": "React functional component rendering the footer section with styling and text."}], "calls": [], "search-terms": ["Footer", "React component", "footer element", "CSS classes"], "state": 2, "file_id": 14, "knowledge_revision": 32, "git_revision": "", "ctags": [], "hash": "0307dc05848624d59d54d738086735bb", "format-version": 4, "code-base-name": "web_frontend", "filename": "web_frontend/src/components/Footer.tsx", "revision_history": [{"32": ""}]}